sc2bench/__init__.py
sc2bench/analysis.py
sc2bench/loss.py
sc2bench/common/__init__.py
sc2bench/common/config_util.py
sc2bench/models/__init__.py
sc2bench/models/backbone.py
sc2bench/models/layer.py
sc2bench/models/registry.py
sc2bench/models/wrapper.py
sc2bench/models/detection/__init__.py
sc2bench/models/detection/base.py
sc2bench/models/detection/rcnn.py
sc2bench/models/detection/registry.py
sc2bench/models/detection/transform.py
sc2bench/models/detection/wrapper.py
sc2bench/models/segmentation/__init__.py
sc2bench/models/segmentation/base.py
sc2bench/models/segmentation/deeplabv3.py
sc2bench/models/segmentation/registry.py
sc2bench/models/segmentation/wrapper.py
sc2bench/transforms/__init__.py
sc2bench/transforms/codec.py
sc2bench/transforms/collator.py
sc2bench/transforms/misc.py
sc2bench-0.1.0.dist-info/LICENSE
sc2bench-0.1.0.dist-info/METADATA
sc2bench-0.1.0.dist-info/WHEEL
sc2bench-0.1.0.dist-info/top_level.txt
sc2bench-0.1.0.dist-info/RECORD
