Metadata-Version: 2.1
Name: sc2bench
Version: 0.1.0
Summary: SC2 Benchmark: Supervised Compression for Split Computing.
Home-page: https://github.com/yoshitomo-matsubara/sc2-benchmark
Author: Yoshitomo Matsubara
License: MIT
Requires-Python: >=3.9
License-File: LICENSE
Requires-Dist: torch>=2.0.0
Requires-Dist: torchvision>=0.15.1
Requires-Dist: numpy
Requires-Dist: pyyaml>=6.0.0
Requires-Dist: scipy
Requires-Dist: cython
Requires-Dist: pycocotools>=2.0.2
Requires-Dist: torchdistill>=1.0.0
Requires-Dist: compressai>=1.2.3
Requires-Dist: timm>=1.0.3
Provides-Extra: test
Requires-Dist: pytest; extra == "test"
Provides-Extra: docs
Requires-Dist: sphinx; extra == "docs"
Requires-Dist: sphinx_rtd_theme; extra == "docs"
Requires-Dist: sphinxcontrib-youtube; extra == "docs"
